[{"NomEspecie":"Aegaeon lacazei","NomComu":null,"Biomassa":"0.007","ClassificacioCaptura":"Rebuig"},{"NomEspecie":"Ancistroteuthis lichtensteinii","NomComu":null,"Biomassa":"0.047","ClassificacioCaptura":"Rebuig"},{"NomEspecie":"Arctozenus risso","NomComu":null,"Biomassa":"0.028","ClassificacioCaptura":"Rebuig"},{"NomEspecie":"Aristeus antennatus","NomComu":"Gamba rosada","Biomassa":"60.352","ClassificacioCaptura":"Comercial"},{"NomEspecie":"Arts de pesca","NomComu":null,"Biomassa":"0.011","ClassificacioCaptura":"Residus"},{"NomEspecie":"Ceratoscopelus maderensis","NomComu":null,"Biomassa":"0.009","ClassificacioCaptura":"Rebuig"},{"NomEspecie":"Chauliodus sloani","NomComu":null,"Biomassa":"0.175","ClassificacioCaptura":"Rebuig"},{"NomEspecie":"Closques","NomComu":null,"Biomassa":"0.521","ClassificacioCaptura":"Residus"},{"NomEspecie":"Conger conger","NomComu":"Congre","Biomassa":"9.784","ClassificacioCaptura":"Comercial"},{"NomEspecie":"Cordes","NomComu":null,"Biomassa":"0.049","ClassificacioCaptura":"Residus"},{"NomEspecie":"Dardanus arrosor","NomComu":null,"Biomassa":"0.132","ClassificacioCaptura":"Rebuig"},{"NomEspecie":"Deosergestes henseni","NomComu":null,"Biomassa":"0.007","ClassificacioCaptura":"Rebuig"},{"NomEspecie":"Eusergestes arcticus","NomComu":null,"Biomassa":"0.003","ClassificacioCaptura":"Rebuig"},{"NomEspecie":"Evermannella balbo","NomComu":null,"Biomassa":"0.048","ClassificacioCaptura":"Rebuig"},{"NomEspecie":"Galeus melastomus","NomComu":"Moixina","Biomassa":"16.867","ClassificacioCaptura":"Comercial"},{"NomEspecie":"Galeus melastomus","NomComu":"Moixina","Biomassa":"7.699","ClassificacioCaptura":"Rebuig"},{"NomEspecie":"Geryon longipes","NomComu":"Cranc de la gamba","Biomassa":"17.011","ClassificacioCaptura":"Comercial"},{"NomEspecie":"Geryon longipes","NomComu":"Cranc de la gamba","Biomassa":"0.089","ClassificacioCaptura":"Rebuig"},{"NomEspecie":"Goneplax rhomboides","NomComu":null,"Biomassa":"0.019","ClassificacioCaptura":"Rebuig"},{"NomEspecie":"Lampanyctus crocodilus","NomComu":null,"Biomassa":"0.158","ClassificacioCaptura":"Rebuig"},{"NomEspecie":"Lepidopus caudatus","NomComu":"Sabre","Biomassa":"0.735","ClassificacioCaptura":"Rebuig"},{"NomEspecie":"Macropipus tuberculatus","NomComu":null,"Biomassa":"0.070","ClassificacioCaptura":"Comercial"},{"NomEspecie":"Merluccius merluccius","NomComu":"Lluç","Biomassa":"8.694","ClassificacioCaptura":"Comercial"},{"NomEspecie":"Micromesistius poutassou","NomComu":"Maire","Biomassa":"10.684","ClassificacioCaptura":"Comercial"},{"NomEspecie":"Munida speciosa","NomComu":null,"Biomassa":"0.022","ClassificacioCaptura":"Rebuig"},{"NomEspecie":"Nezumia aequalis","NomComu":null,"Biomassa":"0.485","ClassificacioCaptura":"Rebuig"},{"NomEspecie":"Ous de Raja spp.","NomComu":null,"Biomassa":"0.043","ClassificacioCaptura":"Rebuig"},{"NomEspecie":"Ous de Scyliorhinus canicula","NomComu":null,"Biomassa":"0.039","ClassificacioCaptura":"Rebuig"},{"NomEspecie":"Paromola cuvieri","NomComu":"Cabrot","Biomassa":"0.688","ClassificacioCaptura":"Comercial"},{"NomEspecie":"Pasiphaea multidentata","NomComu":null,"Biomassa":"2.073","ClassificacioCaptura":"Comercial"},{"NomEspecie":"Pasiphaea multidentata","NomComu":null,"Biomassa":"0.230","ClassificacioCaptura":"Rebuig"},{"NomEspecie":"Phycis blennoides","NomComu":"Bròtola de fang","Biomassa":"12.414","ClassificacioCaptura":"Comercial"},{"NomEspecie":"Phycis blennoides","NomComu":"Bròtola de fang","Biomassa":"0.270","ClassificacioCaptura":"Rebuig"},{"NomEspecie":"Plàstic","NomComu":null,"Biomassa":"0.027","ClassificacioCaptura":"Residus"},{"NomEspecie":"Plesionika heterocarpus","NomComu":"Gamba borda","Biomassa":"0.005","ClassificacioCaptura":"Rebuig"},{"NomEspecie":"Plesionika martia","NomComu":null,"Biomassa":"2.036","ClassificacioCaptura":"Comercial"},{"NomEspecie":"Plesionika martia","NomComu":null,"Biomassa":"0.034","ClassificacioCaptura":"Rebuig"},{"NomEspecie":"Polycheles typhlops","NomComu":null,"Biomassa":"0.359","ClassificacioCaptura":"Comercial"},{"NomEspecie":"Polycheles typhlops","NomComu":null,"Biomassa":"0.060","ClassificacioCaptura":"Rebuig"},{"NomEspecie":"Restes orgàniques marines","NomComu":null,"Biomassa":"0.014","ClassificacioCaptura":"Residus"},{"NomEspecie":"Scyliorhinus canicula","NomComu":"Gat","Biomassa":"8.246","ClassificacioCaptura":"Rebuig"},{"NomEspecie":"Stomias boa","NomComu":null,"Biomassa":"0.079","ClassificacioCaptura":"Rebuig"},{"NomEspecie":"Todarodes sagittatus","NomComu":"Canana","Biomassa":"0.634","ClassificacioCaptura":"Comercial"},{"NomEspecie":"Trachyrhyncus scabrus","NomComu":null,"Biomassa":"0.289","ClassificacioCaptura":"Rebuig"},{"NomEspecie":"Vegetals terrestres","NomComu":null,"Biomassa":"0.428","ClassificacioCaptura":"Residus"}]