[{"NomEspecie":"Altres algues marines","NomComu":null,"Biomassa":"0.512","ClassificacioCaptura":"Residus"},{"NomEspecie":"Bathypolypus sponsalis","NomComu":null,"Biomassa":"1.365","ClassificacioCaptura":"Rebuig"},{"NomEspecie":"Closques","NomComu":null,"Biomassa":"0.452","ClassificacioCaptura":"Residus"},{"NomEspecie":"Coelorinchus caelorhincus","NomComu":null,"Biomassa":"0.220","ClassificacioCaptura":"Rebuig"},{"NomEspecie":"Cordes","NomComu":null,"Biomassa":"0.042","ClassificacioCaptura":"Residus"},{"NomEspecie":"Dardanus arrosor","NomComu":null,"Biomassa":"0.085","ClassificacioCaptura":"Rebuig"},{"NomEspecie":"Echinaster sepositus","NomComu":null,"Biomassa":"0.561","ClassificacioCaptura":"Rebuig"},{"NomEspecie":"Etmopterus spinax","NomComu":"Negret","Biomassa":"0.341","ClassificacioCaptura":"Rebuig"},{"NomEspecie":"Helicolenus dactylopterus","NomComu":"Penegal","Biomassa":"2.755","ClassificacioCaptura":"Comercial"},{"NomEspecie":"Hoplostethus mediterraneus","NomComu":"Rellotge","Biomassa":"0.124","ClassificacioCaptura":"Rebuig"},{"NomEspecie":"Hormathia alba","NomComu":null,"Biomassa":"0.062","ClassificacioCaptura":"Rebuig"},{"NomEspecie":"Hymenocephalus italicus","NomComu":null,"Biomassa":"0.128","ClassificacioCaptura":"Rebuig"},{"NomEspecie":"Illex coindetii","NomComu":"Canana Vera","Biomassa":"0.201","ClassificacioCaptura":"Rebuig"},{"NomEspecie":"Lepidopus caudatus","NomComu":"Sabre","Biomassa":"1.367","ClassificacioCaptura":"Rebuig"},{"NomEspecie":"Lepidorhombus boscii","NomComu":"Bruixa de quatre taques","Biomassa":"9.517","ClassificacioCaptura":"Comercial"},{"NomEspecie":"Lepidorhombus boscii","NomComu":"Bruixa de quatre taques","Biomassa":"0.338","ClassificacioCaptura":"Rebuig"},{"NomEspecie":"Lytocarpia myriophyllum","NomComu":null,"Biomassa":"0.008","ClassificacioCaptura":"Rebuig"},{"NomEspecie":"Macropipus tuberculatus","NomComu":null,"Biomassa":"0.097","ClassificacioCaptura":"Rebuig"},{"NomEspecie":"Merluccius merluccius","NomComu":"Lluç","Biomassa":"29.335","ClassificacioCaptura":"Comercial"},{"NomEspecie":"Merluccius merluccius","NomComu":"Lluç","Biomassa":"1.709","ClassificacioCaptura":"Rebuig"},{"NomEspecie":"Micromesistius poutassou","NomComu":"Maire","Biomassa":"0.746","ClassificacioCaptura":"Comercial"},{"NomEspecie":"Molva macrophthalma","NomComu":"Escolà","Biomassa":"6.928","ClassificacioCaptura":"Comercial"},{"NomEspecie":"Nephrops norvegicus","NomComu":"Escamarlà","Biomassa":"29.095","ClassificacioCaptura":"Comercial"},{"NomEspecie":"Pagurus excavatus","NomComu":null,"Biomassa":"0.075","ClassificacioCaptura":"Rebuig"},{"NomEspecie":"Parapenaeus longirostris","NomComu":"Gamba blanca","Biomassa":"9.090","ClassificacioCaptura":"Comercial"},{"NomEspecie":"Parapenaeus longirostris","NomComu":"Gamba blanca","Biomassa":"0.835","ClassificacioCaptura":"Rebuig"},{"NomEspecie":"Pasiphaea multidentata","NomComu":null,"Biomassa":"0.186","ClassificacioCaptura":"Rebuig"},{"NomEspecie":"Phycis blennoides","NomComu":"Bròtola de fang","Biomassa":"30.668","ClassificacioCaptura":"Comercial"},{"NomEspecie":"Plàstic","NomComu":null,"Biomassa":"0.904","ClassificacioCaptura":"Residus"},{"NomEspecie":"Plesionika heterocarpus","NomComu":"Gamba borda","Biomassa":"0.062","ClassificacioCaptura":"Rebuig"},{"NomEspecie":"Plesionika martia","NomComu":null,"Biomassa":"1.392","ClassificacioCaptura":"Rebuig"},{"NomEspecie":"Processa canaliculata","NomComu":null,"Biomassa":"0.104","ClassificacioCaptura":"Rebuig"},{"NomEspecie":"Restes orgàniques marines","NomComu":null,"Biomassa":"0.645","ClassificacioCaptura":"Residus"},{"NomEspecie":"Scaeurgus unicirrhus","NomComu":null,"Biomassa":"2.270","ClassificacioCaptura":"Rebuig"},{"NomEspecie":"Scyliorhinus canicula","NomComu":"Gat","Biomassa":"99.516","ClassificacioCaptura":"Rebuig"},{"NomEspecie":"Solenocera membranacea","NomComu":"Gambeta de fons","Biomassa":"0.205","ClassificacioCaptura":"Rebuig"},{"NomEspecie":"Tethya aurantium","NomComu":null,"Biomassa":"0.055","ClassificacioCaptura":"Rebuig"},{"NomEspecie":"Tovalloletes","NomComu":null,"Biomassa":"0.904","ClassificacioCaptura":"Residus"},{"NomEspecie":"Vegetals terrestres","NomComu":null,"Biomassa":"22.997","ClassificacioCaptura":"Residus"}]