[{"NomEspecie":"Actinia sp. 2","NomComu":null,"Biomassa":"0.102","ClassificacioCaptura":"Rebuig"},{"NomEspecie":"Adamsia palliata","NomComu":null,"Biomassa":"0.043","ClassificacioCaptura":"Rebuig"},{"NomEspecie":"Alcyonium palmatum","NomComu":null,"Biomassa":"0.957","ClassificacioCaptura":"Rebuig"},{"NomEspecie":"Aphrodita aculeata","NomComu":null,"Biomassa":"0.119","ClassificacioCaptura":"Rebuig"},{"NomEspecie":"Arts de pesca","NomComu":null,"Biomassa":"0.073","ClassificacioCaptura":"Residus"},{"NomEspecie":"Astropecten irregularis","NomComu":null,"Biomassa":"0.099","ClassificacioCaptura":"Rebuig"},{"NomEspecie":"Calliactis parasitica","NomComu":null,"Biomassa":"0.465","ClassificacioCaptura":"Rebuig"},{"NomEspecie":"Capros aper","NomComu":"Xavo","Biomassa":"0.719","ClassificacioCaptura":"Rebuig"},{"NomEspecie":"Carbó","NomComu":null,"Biomassa":"2.563","ClassificacioCaptura":"Residus"},{"NomEspecie":"Closques","NomComu":null,"Biomassa":"10.833","ClassificacioCaptura":"Residus"},{"NomEspecie":"Coelorinchus caelorhincus","NomComu":null,"Biomassa":"1.910","ClassificacioCaptura":"Rebuig"},{"NomEspecie":"Conger conger","NomComu":"Congre","Biomassa":"3.905","ClassificacioCaptura":"Comercial"},{"NomEspecie":"Conger conger","NomComu":"Congre","Biomassa":"9.902","ClassificacioCaptura":"Rebuig"},{"NomEspecie":"Dardanus arrosor","NomComu":null,"Biomassa":"1.869","ClassificacioCaptura":"Rebuig"},{"NomEspecie":"Eledone cirrhosa","NomComu":"Pop blanc","Biomassa":"9.993","ClassificacioCaptura":"Comercial"},{"NomEspecie":"Euspira fusca","NomComu":null,"Biomassa":"0.148","ClassificacioCaptura":"Rebuig"},{"NomEspecie":"Funiculina quadrangularis","NomComu":null,"Biomassa":"0.006","ClassificacioCaptura":"Rebuig"},{"NomEspecie":"Gadiculus argenteus","NomComu":null,"Biomassa":"0.368","ClassificacioCaptura":"Rebuig"},{"NomEspecie":"Helicolenus dactylopterus","NomComu":"Penegal","Biomassa":"27.476","ClassificacioCaptura":"Comercial"},{"NomEspecie":"Helicolenus dactylopterus","NomComu":"Penegal","Biomassa":"0.484","ClassificacioCaptura":"Rebuig"},{"NomEspecie":"Hormathia alba","NomComu":null,"Biomassa":"0.322","ClassificacioCaptura":"Rebuig"},{"NomEspecie":"Illex coindetii","NomComu":"Canana Vera","Biomassa":"7.420","ClassificacioCaptura":"Comercial"},{"NomEspecie":"Illex coindetii","NomComu":"Canana Vera","Biomassa":"3.799","ClassificacioCaptura":"Rebuig"},{"NomEspecie":"Lepidopus caudatus","NomComu":"Sabre","Biomassa":"0.246","ClassificacioCaptura":"Rebuig"},{"NomEspecie":"Lepidorhombus boscii","NomComu":"Bruixa de quatre taques","Biomassa":"8.148","ClassificacioCaptura":"Comercial"},{"NomEspecie":"Lepidorhombus boscii","NomComu":"Bruixa de quatre taques","Biomassa":"0.807","ClassificacioCaptura":"Rebuig"},{"NomEspecie":"Liocarcinus depurator","NomComu":"Cranc de sopa","Biomassa":"0.287","ClassificacioCaptura":"Rebuig"},{"NomEspecie":"Lophius budegassa","NomComu":"Rap vermell","Biomassa":"7.582","ClassificacioCaptura":"Comercial"},{"NomEspecie":"Lophius budegassa","NomComu":"Rap vermell","Biomassa":"2.914","ClassificacioCaptura":"Rebuig"},{"NomEspecie":"Lophius piscatorius","NomComu":"Rap","Biomassa":"139.097","ClassificacioCaptura":"Comercial"},{"NomEspecie":"Lytocarpia myriophyllum","NomComu":null,"Biomassa":"0.092","ClassificacioCaptura":"Rebuig"},{"NomEspecie":"Macropipus tuberculatus","NomComu":null,"Biomassa":"0.063","ClassificacioCaptura":"Comercial"},{"NomEspecie":"Macropodia tenuirostris","NomComu":null,"Biomassa":"0.018","ClassificacioCaptura":"Rebuig"},{"NomEspecie":"Medorippe lanata","NomComu":null,"Biomassa":"0.111","ClassificacioCaptura":"Rebuig"},{"NomEspecie":"Merluccius merluccius","NomComu":"Lluç","Biomassa":"13.193","ClassificacioCaptura":"Comercial"},{"NomEspecie":"Microcosmus vulgaris","NomComu":"Bunyol de mar","Biomassa":"0.404","ClassificacioCaptura":"Rebuig"},{"NomEspecie":"Micromesistius poutassou","NomComu":"Maire","Biomassa":"1.190","ClassificacioCaptura":"Comercial"},{"NomEspecie":"Molva macrophthalma","NomComu":"Escolà","Biomassa":"3.342","ClassificacioCaptura":"Comercial"},{"NomEspecie":"Molva macrophthalma","NomComu":"Escolà","Biomassa":"0.339","ClassificacioCaptura":"Rebuig"},{"NomEspecie":"Monodaeus couchii","NomComu":null,"Biomassa":"0.018","ClassificacioCaptura":"Rebuig"},{"NomEspecie":"Mullus surmuletus","NomComu":"Moll de roca","Biomassa":"0.821","ClassificacioCaptura":"Comercial"},{"NomEspecie":"Nephrops norvegicus","NomComu":"Escamarlà","Biomassa":"19.850","ClassificacioCaptura":"Comercial"},{"NomEspecie":"Nephrops norvegicus","NomComu":"Escamarlà","Biomassa":"0.121","ClassificacioCaptura":"Rebuig"},{"NomEspecie":"Pagellus bogaraveo","NomComu":"Besuc de la piga","Biomassa":"0.881","ClassificacioCaptura":"Comercial"},{"NomEspecie":"Pagellus bogaraveo","NomComu":"Besuc de la piga","Biomassa":"18.583","ClassificacioCaptura":"Rebuig"},{"NomEspecie":"Pagurus prideaux","NomComu":null,"Biomassa":"0.693","ClassificacioCaptura":"Rebuig"},{"NomEspecie":"Parapenaeus longirostris","NomComu":"Gamba blanca","Biomassa":"4.373","ClassificacioCaptura":"Comercial"},{"NomEspecie":"Parapenaeus longirostris","NomComu":"Gamba blanca","Biomassa":"0.233","ClassificacioCaptura":"Rebuig"},{"NomEspecie":"Pasiphaea sivado","NomComu":null,"Biomassa":"0.021","ClassificacioCaptura":"Rebuig"},{"NomEspecie":"Pennatula phosphorea","NomComu":null,"Biomassa":"0.031","ClassificacioCaptura":"Rebuig"},{"NomEspecie":"Phycis blennoides","NomComu":"Bròtola de fang","Biomassa":"72.977","ClassificacioCaptura":"Comercial"},{"NomEspecie":"Phycis blennoides","NomComu":"Bròtola de fang","Biomassa":"2.794","ClassificacioCaptura":"Rebuig"},{"NomEspecie":"Plantes marines","NomComu":null,"Biomassa":"0.505","ClassificacioCaptura":"Residus"},{"NomEspecie":"Plàstic","NomComu":null,"Biomassa":"0.914","ClassificacioCaptura":"Residus"},{"NomEspecie":"Pteria hirundo","NomComu":null,"Biomassa":"0.050","ClassificacioCaptura":"Rebuig"},{"NomEspecie":"Pteroeides griseum","NomComu":null,"Biomassa":"0.127","ClassificacioCaptura":"Rebuig"},{"NomEspecie":"Raja clavata","NomComu":"Clavellada","Biomassa":"0.671","ClassificacioCaptura":"Rebuig"},{"NomEspecie":"Restes orgàniques marines","NomComu":null,"Biomassa":"4.760","ClassificacioCaptura":"Residus"},{"NomEspecie":"Rossia macrosoma","NomComu":null,"Biomassa":"1.214","ClassificacioCaptura":"Comercial"},{"NomEspecie":"Rossia macrosoma","NomComu":null,"Biomassa":"1.341","ClassificacioCaptura":"Rebuig"},{"NomEspecie":"Scaeurgus unicirrhus","NomComu":null,"Biomassa":"2.530","ClassificacioCaptura":"Comercial"},{"NomEspecie":"Scyliorhinus canicula","NomComu":"Gat","Biomassa":"269.448","ClassificacioCaptura":"Rebuig"},{"NomEspecie":"Sepietta oweniana","NomComu":"Morrallet","Biomassa":"0.540","ClassificacioCaptura":"Rebuig"},{"NomEspecie":"Solenocera membranacea","NomComu":"Gambeta de fons","Biomassa":"0.069","ClassificacioCaptura":"Rebuig"},{"NomEspecie":"Todarodes sagittatus","NomComu":"Canana","Biomassa":"7.305","ClassificacioCaptura":"Comercial"},{"NomEspecie":"Todaropsis eblanae","NomComu":null,"Biomassa":"2.350","ClassificacioCaptura":"Rebuig"},{"NomEspecie":"Trachurus trachurus","NomComu":"Sorell","Biomassa":"13.182","ClassificacioCaptura":"Rebuig"},{"NomEspecie":"Trigla lyra","NomComu":"Garneu","Biomassa":"11.940","ClassificacioCaptura":"Comercial"},{"NomEspecie":"Trigla lyra","NomComu":"Garneu","Biomassa":"1.848","ClassificacioCaptura":"Rebuig"},{"NomEspecie":"Vegetals terrestres","NomComu":null,"Biomassa":"8.941","ClassificacioCaptura":"Residus"},{"NomEspecie":"Vidre/Ceràmica","NomComu":null,"Biomassa":"0.795","ClassificacioCaptura":"Residus"}]