[{"NomEspecie":"Aristeus antennatus","NomComu":"Gamba rosada","Biomassa":"73.709","ClassificacioCaptura":"Comercial"},{"NomEspecie":"Chauliodus sloani","NomComu":null,"Biomassa":"0.728","ClassificacioCaptura":"Rebuig"},{"NomEspecie":"Coelorinchus caelorhincus","NomComu":null,"Biomassa":"1.420","ClassificacioCaptura":"Rebuig"},{"NomEspecie":"Conger conger","NomComu":"Congre","Biomassa":"4.778","ClassificacioCaptura":"Comercial"},{"NomEspecie":"Conger conger","NomComu":"Congre","Biomassa":"6.691","ClassificacioCaptura":"Rebuig"},{"NomEspecie":"Cymbulia spp.","NomComu":null,"Biomassa":"0.180","ClassificacioCaptura":"Rebuig"},{"NomEspecie":"Fusta","NomComu":null,"Biomassa":"0.037","ClassificacioCaptura":"Residus"},{"NomEspecie":"Galeus melastomus","NomComu":"Moixina","Biomassa":"30.789","ClassificacioCaptura":"Rebuig"},{"NomEspecie":"Histioteuthis bonnellii","NomComu":null,"Biomassa":"0.994","ClassificacioCaptura":"Rebuig"},{"NomEspecie":"Hoplostethus mediterraneus","NomComu":"Rellotge","Biomassa":"3.762","ClassificacioCaptura":"Rebuig"},{"NomEspecie":"Hymenocephalus italicus","NomComu":null,"Biomassa":"0.091","ClassificacioCaptura":"Rebuig"},{"NomEspecie":"Lampanyctus crocodilus","NomComu":null,"Biomassa":"29.671","ClassificacioCaptura":"Rebuig"},{"NomEspecie":"Micromesistius poutassou","NomComu":"Maire","Biomassa":"11.663","ClassificacioCaptura":"Comercial"},{"NomEspecie":"Molva macrophthalma","NomComu":"Escolà","Biomassa":"2.319","ClassificacioCaptura":"Comercial"},{"NomEspecie":"Pasiphaea sivado","NomComu":null,"Biomassa":"0.071","ClassificacioCaptura":"Comercial"},{"NomEspecie":"Pasiphaea sivado","NomComu":null,"Biomassa":"0.318","ClassificacioCaptura":"Rebuig"},{"NomEspecie":"Phycis blennoides","NomComu":"Bròtola de fang","Biomassa":"51.533","ClassificacioCaptura":"Comercial"},{"NomEspecie":"Plantes marines","NomComu":null,"Biomassa":"0.087","ClassificacioCaptura":"Residus"},{"NomEspecie":"Plesionika martia","NomComu":null,"Biomassa":"4.224","ClassificacioCaptura":"Comercial"},{"NomEspecie":"Plesionika martia","NomComu":null,"Biomassa":"0.125","ClassificacioCaptura":"Rebuig"},{"NomEspecie":"Polycheles typhlops","NomComu":null,"Biomassa":"0.470","ClassificacioCaptura":"Rebuig"},{"NomEspecie":"Restes orgàniques marines","NomComu":null,"Biomassa":"1.164","ClassificacioCaptura":"Residus"},{"NomEspecie":"Robustosergia robusta","NomComu":null,"Biomassa":"0.571","ClassificacioCaptura":"Comercial"},{"NomEspecie":"Robustosergia robusta","NomComu":null,"Biomassa":"0.068","ClassificacioCaptura":"Rebuig"},{"NomEspecie":"Spicara maena","NomComu":"Xucla","Biomassa":"0.352","ClassificacioCaptura":"Rebuig"},{"NomEspecie":"Todarodes sagittatus","NomComu":"Canana","Biomassa":"1.442","ClassificacioCaptura":"Comercial"},{"NomEspecie":"Trachyrhyncus scabrus","NomComu":null,"Biomassa":"16.042","ClassificacioCaptura":"Rebuig"}]